LICENSE
README.md
setup.py
sentence_store/__init__.py
sentence_store/main.py
sentence_store/requirements.txt
sentence_store/tools.py
sentence_store.egg-info/PKG-INFO
sentence_store.egg-info/SOURCES.txt
sentence_store.egg-info/dependency_links.txt
sentence_store.egg-info/not-zip-safe
sentence_store.egg-info/requires.txt
sentence_store.egg-info/top_level.txt