Metadata-Version: 2.1
Name: sentence-store
Version: 0.4.1
Summary: Tool to extract and store sentence embeddings to a fast and scalable vector db
Home-page: https://github.com/ptarau/sentence_store.git
Author: Paul Tarau
Author-email: paul.tarau@gmail.com
License: MIT
License-File: LICENSE
